pyqgen/__init__.py
pyqgen/pyqgen-0.1.1-py2.py3-none-any.whl
pyqgen/pyqgen-0.1.1.tar.gz
pyqgen/pyqgen.py
pyqgen-0.3.dist-info/METADATA
pyqgen-0.3.dist-info/WHEEL
pyqgen-0.3.dist-info/entry_points.txt
pyqgen-0.3.dist-info/licenses/LICENSE
pyqgen-0.3.dist-info/RECORD
