Metadata-Version: 2.1
Name: pyqgen
Version: 0.3
Summary: Generate questions from orgmode files
Project-URL: Homepage, http://github.com/glipari/pyqgen
Author-email: Giuseppe Lipari <giuseppe.lipari@univ-lille.fr>
License-Expression: MIT
License-File: LICENSE
Requires-Dist: openpyxl
Requires-Dist: orgparse
